s3func/__init__.py
s3func/b2.py
s3func/http_url.py
s3func/s3.py
s3func/utils.py
s3func/tests/__init__.py
s3func/tests/test_s3func.py
s3func-0.7.2.dist-info/METADATA
s3func-0.7.2.dist-info/WHEEL
s3func-0.7.2.dist-info/licenses/LICENSE
s3func-0.7.2.dist-info/RECORD
