Metadata-Version: 2.4
Name: s3func
Version: 0.7.2
Summary: Simple functions for working with S3
Project-URL: Documentation, https://mullenkamp.github.io/s3func/
Project-URL: Source, https://github.com/mullenkamp/s3func
Author-email: Mike Kittridge <mullenkamp1@gmail.com>
License-File: LICENSE
Classifier: Programming Language :: Python :: 3 :: Only
Requires-Python: >=3.9
Requires-Dist: boto3<1.36
Requires-Dist: orjson
Requires-Dist: urllib3>=2
